hestia_earth/utils/__init__.py
hestia_earth/utils/api.py
hestia_earth/utils/blank_node.py
hestia_earth/utils/calculation_status.py
hestia_earth/utils/cycle.py
hestia_earth/utils/date.py
hestia_earth/utils/descriptive_stats.py
hestia_earth/utils/emission.py
hestia_earth/utils/lookup.py
hestia_earth/utils/lookup_utils.py
hestia_earth/utils/model.py
hestia_earth/utils/pipeline.py
hestia_earth/utils/request.py
hestia_earth/utils/stats.py
hestia_earth/utils/table.py
hestia_earth/utils/term.py
hestia_earth/utils/tools.py
hestia_earth/utils/version.py
hestia_earth/utils/pivot/__init__.py
hestia_earth/utils/pivot/_shared.py
hestia_earth/utils/pivot/pivot_csv.py
hestia_earth/utils/pivot/pivot_json.py
hestia_earth/utils/storage/__init__.py
hestia_earth/utils/storage/_azure_client.py
hestia_earth/utils/storage/_local_client.py
hestia_earth/utils/storage/_s3_client.py
hestia_earth/utils/storage/_sns_client.py
hestia_earth_utils-0.16.15.data/scripts/hestia-format-upload
hestia_earth_utils-0.16.15.data/scripts/hestia-pivot-csv
hestia_earth_utils-0.16.15.dist-info/METADATA
hestia_earth_utils-0.16.15.dist-info/WHEEL
hestia_earth_utils-0.16.15.dist-info/top_level.txt
hestia_earth_utils-0.16.15.dist-info/RECORD
