Metadata-Version: 2.4
Name: hestia_earth_utils
Version: 0.16.15
Summary: HESTIA's utils library
Home-page: https://gitlab.com/hestia-earth/hestia-utils
Author: HESTIA Team
Author-email: guillaumeroyer.mail@gmail.com
License: MIT
Classifier: Programming Language :: Python :: 3.12
Requires-Python: >=3.12
Requires-Dist: hestia-earth-schema>=35.0.1
Requires-Dist: requests>=2.24.0
Requires-Dist: urllib3~=1.26.0
Requires-Dist: python-dateutil>=2.8.1
Requires-Dist: pandas>=2
Requires-Dist: flatten_json
Dynamic: author
Dynamic: author-email
Dynamic: classifier
Dynamic: description
Dynamic: description-content-type
Dynamic: home-page
Dynamic: license
Dynamic: requires-dist
Dynamic: requires-python
Dynamic: summary
